bbtkv2/__init__.py
bbtkv2/bbtkv2.py
bbtkv2-0.3.dist-info/LICENSE
bbtkv2-0.3.dist-info/METADATA
bbtkv2-0.3.dist-info/WHEEL
bbtkv2-0.3.dist-info/top_level.txt
bbtkv2-0.3.dist-info/RECORD
