Metadata-Version: 2.1
Name: bbtkv2
Version: 0.3
Summary: Code to control the BlackBox ToolKit v2 device for audio-visual timing checks
Home-page: https://github.com/chrplr/bbtkv2_python
Author: Christophe Pallier
Author-email: christophe@pallier.org
Project-URL: Documentation, https://bbtkv2.rtfd.io
Project-URL: Bug Tracker, https://github.com/chrplr/bbtkv2_python/issues
Classifier: Programming Language :: Python :: 3
Classifier: License :: OSI Approved :: GNU Affero General Public License v3
Classifier: Operating System :: OS Independent
Requires-Python: >=3.6
License-File: LICENSE
Requires-Dist: pandas
Requires-Dist: toml
Requires-Dist: pyserial
